biotensor/__init__.py
biotensor/biotensor.py
biotensor-0.0.1.dist-info/DESCRIPTION.rst
biotensor-0.0.1.dist-info/METADATA
biotensor-0.0.1.dist-info/RECORD
biotensor-0.0.1.dist-info/WHEEL
biotensor-0.0.1.dist-info/metadata.json
biotensor-0.0.1.dist-info/top_level.txt
