Metadata-Version: 2.0
Name: biotensor
Version: 0.0.1
Summary: no description
Home-page: UNKNOWN
Author-email: qq525399365@gmail.com
License: UNKNOWN
Platform: UNKNOWN
Classifier: Programming Language :: Python :: 3
Classifier: License :: OSI Approved :: MIT License
Classifier: Operating System :: OS Independent
